receipt_ocr/__about__.py
receipt_ocr/__init__.py
receipt_ocr/cli.py
receipt_ocr/constants.py
receipt_ocr/parsers.py
receipt_ocr/processors.py
receipt_ocr/prompts.py
receipt_ocr/providers.py
receipt_ocr/utils.py
receipt_ocr-0.3.0.dist-info/METADATA
receipt_ocr-0.3.0.dist-info/WHEEL
receipt_ocr-0.3.0.dist-info/entry_points.txt
receipt_ocr-0.3.0.dist-info/licenses/LICENSE
receipt_ocr-0.3.0.dist-info/RECORD
