Metadata-Version: 2.4
Name: receipt-ocr
Version: 0.3.0
Summary: A package for extracting structured data from receipts.
Project-URL: Bug Tracker, https://github.com/bhimrazy/receipt-ocr/issues
Project-URL: Documentation, https://github.com/bhimrazy/receipt-ocr
Project-URL: Download, https://github.com/bhimrazy/receipt-ocr
Project-URL: Homepage, https://github.com/bhimrazy/receipt-ocr
Project-URL: Source Code, https://github.com/bhimrazy/receipt-ocr
Author-email: Bhimraj Yadav <bhimrajyadav977@gmail.com>
License: MIT License
License-File: LICENSE
Keywords: llm,ocr,receipts,tesseract
Classifier: Development Status :: 4 - Beta
Classifier: Environment :: Console
Classifier: Intended Audience :: Developers
Classifier: License :: OSI Approved :: MIT License
Classifier: Natural Language :: English
Classifier: Operating System :: OS Independent
Classifier: Programming Language :: Python :: 3 :: Only
Classifier: Programming Language :: Python :: 3.9
Classifier: Programming Language :: Python :: 3.10
Classifier: Programming Language :: Python :: 3.11
Classifier: Programming Language :: Python :: 3.12
Classifier: Programming Language :: Python :: 3.13
Classifier: Topic :: Scientific/Engineering :: Artificial Intelligence
Classifier: Topic :: Scientific/Engineering :: Information Analysis
Classifier: Topic :: Software Development :: Libraries :: Python Modules
Requires-Python: >=3.9
Requires-Dist: openai
Requires-Dist: pillow
Requires-Dist: python-dotenv
